Metadata-Version: 2.1
Name: odoo12-addon-l10n-it-vat-statement-communication
Version: 12.0.1.6.1
Summary: Comunicazione liquidazione IVA ed esportazione file xmlconforme alle specifiche dell'Agenzia delle Entrate
Home-page: https://github.com/OCA/l10n-italy
Author: Openforce di Camilli Alessandro, Odoo Community Association (OCA)
Author-email: support@odoo-community.org
License: AGPL-3
Platform: UNKNOWN
Classifier: Programming Language :: Python
Classifier: Framework :: Odoo
Classifier: License :: OSI Approved :: GNU Affero General Public License v3
Requires-Python: >=3.5
Requires-Dist: odoo12-addon-account-vat-period-end-statement
Requires-Dist: odoo12-addon-l10n-it-codici-carica
Requires-Dist: odoo12-addon-l10n-it-fiscalcode
Requires-Dist: odoo (<12.1dev,>=12.0a)
